{
  "type": "minecraft:crafting_shaped",
  "pattern": [
    " GN",
    "RSG",
    "SR "
  ],
  "key": {
    "G": {
      "item": "minecraft:gold_ingot"
    },
    "R": {
      "item": "minecraft:redstone"
    },
    "S": {
      "item": "minecraft:stick"
    },
    "N": {
      "item": "minecraft:netherite_ingot"
    }
  },
  "result": {
    "id": "minecraft:debug_stick",
    "count": 1,
    "components":{
      "custom_name": "[{'text':'MarliWrench','italic':true}]",
      "lore": ["{'text':'La plus simple des façons de modifier vos blockStates.','italic':false}"],
      "custom_data": {"holywrench":true}
    }
  }
}